django_simple_bulma/__init__.py
django_simple_bulma/apps.py
django_simple_bulma/finders.py
django_simple_bulma/settings.py
django_simple_bulma/utils.py
django_simple_bulma/__pycache__/__init__.cpython-313.pyc
django_simple_bulma/__pycache__/apps.cpython-313.pyc
django_simple_bulma/__pycache__/css_variables.cpython-313.pyc
django_simple_bulma/__pycache__/finders.cpython-313.pyc
django_simple_bulma/__pycache__/utils.cpython-313.pyc
django_simple_bulma/bulma/sass/base/_all.sass
django_simple_bulma/bulma/sass/base/animations.sass
django_simple_bulma/bulma/sass/base/generic.sass
django_simple_bulma/bulma/sass/base/helpers.sass
django_simple_bulma/bulma/sass/base/minireset.sass
django_simple_bulma/bulma/sass/components/_all.sass
django_simple_bulma/bulma/sass/components/breadcrumb.sass
django_simple_bulma/bulma/sass/components/card.sass
django_simple_bulma/bulma/sass/components/dropdown.sass
django_simple_bulma/bulma/sass/components/level.sass
django_simple_bulma/bulma/sass/components/media.sass
django_simple_bulma/bulma/sass/components/menu.sass
django_simple_bulma/bulma/sass/components/message.sass
django_simple_bulma/bulma/sass/components/modal.sass
django_simple_bulma/bulma/sass/components/navbar.sass
django_simple_bulma/bulma/sass/components/pagination.sass
django_simple_bulma/bulma/sass/components/panel.sass
django_simple_bulma/bulma/sass/components/tabs.sass
django_simple_bulma/bulma/sass/elements/_all.sass
django_simple_bulma/bulma/sass/elements/box.sass
django_simple_bulma/bulma/sass/elements/button.sass
django_simple_bulma/bulma/sass/elements/container.sass
django_simple_bulma/bulma/sass/elements/content.sass
django_simple_bulma/bulma/sass/elements/form.sass
django_simple_bulma/bulma/sass/elements/icon.sass
django_simple_bulma/bulma/sass/elements/image.sass
django_simple_bulma/bulma/sass/elements/notification.sass
django_simple_bulma/bulma/sass/elements/other.sass
django_simple_bulma/bulma/sass/elements/progress.sass
django_simple_bulma-2.7.1.dist-info/licenses/LICENSE
django_simple_bulma-2.7.1.dist-info/METADATA
django_simple_bulma-2.7.1.dist-info/WHEEL
django_simple_bulma-2.7.1.dist-info/top_level.txt
django_simple_bulma-2.7.1.dist-info/RECORD
