Metadata-Version: 2.4
Name: django-simple-bulma
Version: 2.7.1
Summary: Django application to add the Bulma CSS framework and its extensions
Home-page: https://github.com/python-discord/django-simple-bulma
Author: Python Discord
Author-email: staff@pythondiscord.com
License: MIT
Classifier: Environment :: Web Environment
Classifier: Framework :: Django
Classifier: Framework :: Django :: 4.2
Classifier: Framework :: Django :: 5.2
Classifier: License :: OSI Approved :: MIT License
Classifier: Operating System :: OS Independent
Classifier: Programming Language :: Python
Classifier: Programming Language :: Python :: 3.12
Classifier: Programming Language :: Python :: 3.13
Classifier: Topic :: Internet :: WWW/HTTP
Classifier: Topic :: Internet :: WWW/HTTP :: Dynamic Content
Classifier: Topic :: Software Development :: Libraries :: Python Modules
License-File: LICENSE
Requires-Dist: Django>=4.2
Requires-Dist: libsass~=0.19
Provides-Extra: dev
Requires-Dist: flake8<7.0,>=5.0; extra == "dev"
Requires-Dist: flake8-annotations<4.0,>=2.0; extra == "dev"
Requires-Dist: flake8-bugbear<25.0,>=22.0; extra == "dev"
Requires-Dist: flake8-docstrings<2.0,>=1.6; extra == "dev"
Requires-Dist: flake8-import-order<1.0,>=0.18; extra == "dev"
Requires-Dist: flake8-tidy-imports<5.0,>=4.0; extra == "dev"
Requires-Dist: flake8-todo<1.0,>=0.7; extra == "dev"
Requires-Dist: flake8-string-format<1.0,>=0.3; extra == "dev"
Requires-Dist: pdoc~=0.3; extra == "dev"
Requires-Dist: pep8-naming~=0.9; extra == "dev"
Requires-Dist: pre-commit~=2.1; extra == "dev"
Requires-Dist: PyGithub~=1.43; extra == "dev"
Requires-Dist: wheel~=0.33; extra == "dev"
Requires-Dist: pytest<9.0,>=7.0; extra == "dev"
Requires-Dist: pytest-django<5.0,>=4.5; extra == "dev"
Requires-Dist: pytest-mock<4.0,>=3.6; extra == "dev"
Requires-Dist: coverage[toml]<8.0,>=6.0; extra == "dev"
Dynamic: author
Dynamic: author-email
Dynamic: classifier
Dynamic: description
Dynamic: description-content-type
Dynamic: home-page
Dynamic: license
Dynamic: license-file
Dynamic: provides-extra
Dynamic: requires-dist
Dynamic: summary
